LICENSE.txt
README.md
pyproject.toml
setup.cfg
setup.py
distool/__init__.py
distool.egg-info/PKG-INFO
distool.egg-info/SOURCES.txt
distool.egg-info/dependency_links.txt
distool.egg-info/requires.txt
distool.egg-info/top_level.txt
distool/base/__init__.py
distool/base/estimators.py
distool/data/symptoms.json
distool/estimators/__init__.py
distool/estimators/classifiers.py
distool/feature_extraction/__init__.py
distool/feature_extraction/anamnesis.py
distool/feature_extraction/dumb_extractor.py
distool/feature_extraction/smart_extractor.py
distool/feature_extraction/symptom.py
distool/feature_extraction/symptom_collection.py
distool/feature_extraction/symptom_status.py
distool/interpretation/__init__.py
distool/interpretation/explainer.py
distool/metrics/__init__.py
distool/metrics/extractor/__init__.py
distool/metrics/extractor/compute.py
distool/metrics/extractor/create_showcase.py
distool/models/__init__.py
distool/models/urgency_classifier.py
distool/tests/__init__.py
distool/tests/conftest.py
distool/tests/test_base.py
distool/tests/estimators/__init__.py
distool/tests/estimators/test_classifier.py
distool/tests/estimators/test_fedot_classifier.py
distool/tests/explainer/__init__.py
distool/tests/explainer/test_explainer.py
distool/tests/extractors/__init__.py
distool/tests/extractors/test_symptom_extractor.py
examples/__init__.py
examples/pipeline_example.py